{
    "elements":[
        {"id": 0,
         "name":"alien",
         "type": "physical",
         "weak": ["alien", "radiation", "undead", "water"],
         "strong": ["air", "chaos", "earth", "electricity", "fire", "normal"]},

        {"id": 1,
         "name":"air",
         "type": "special",
         "weak": ["alien", "air", "earth", "evil", "radiation", "plant"],
         "strong": ["electricity", "fire", "ice", "mutation"]},

        {"id": 2,
         "name":"chaos",
         "type": "physical",
         "weak": ["air", "earth", "fire", "plant"],
         "strong": ["alien", "chaos", "mutation", "radiation", "undead", "water"]},

        {"id": 3,
         "name":"earth",
         "type": "physical",
         "weak": ["earth", "metal", "plant", "water"],
         "strong": ["evil", "fire", "undead"]},

        {"id": 4,
         "name":"electricity",
         "type": "special",
         "weak":["alien", "air", "earth", "electricity", "plant"],
         "strong":["holiness", "metal", "water", "undead"]},

        {"id": 5,
         "name":"evil",
         "type": "physical",
         "weak": ["earth", "evil", "radiation", "undead"],
         "strong": ["holiness", "normal", "plant", "ice"]},

        {"id": 6,
         "name":"fire",
         "type": "special",
         "weak": ["air", "earth", "evil", "water"],
         "strong": ["alien", "ice", "metal", "plant", "undead"]},

        {"id": 7,
         "name":"holiness",
         "type": "physical",
         "weak": ["alien", "chaos", "holiness"],
         "strong": ["earth", "evil", "fire", "ice", "mutation", "radiation", "poison", "undead"]},

        {"id": 8,
         "name":"ice",
         "type": "special",
         "weak": ["chaos", "fire", "ice"],
         "strong": ["earth", "holiness", "plant", "undead", "water"]},

        {"id": 9,
         "name":"metal",
         "type": "physical",
         "weak": ["holiness", "ice", "mutation", "water"],
         "strong": ["alien", "chaos", "evil", "radiation", "plant"]},

        {"id": 10,
         "name":"mutatation",
         "type": "physical",
         "weak": ["holiness", "ice", "mutation", "water"],
         "strong": ["alien", "chaos", "evil", "radiation", "plant"]},

        {"id": 11,
         "name":"normal",
         "type": "physical",
         "weak": ["alien", "chaos", "undead"],
         "strong": ["chaos", "earth", "evil", "mutation"]},

        {"id": 12,
         "name":"plant",
         "type": "special",
         "weak": ["chaos", "evil", "fire", "ice", "radiation", "plant"],
         "strong": ["alien", "air", "earth", "holiness", "water"]},

        {"id": 13,
         "name":"poison",
         "type": "physical",
         "weak": ["metal", "mutation", "radiation", "poison", "undead"],
         "strong": ["alien", "chaos", "holiness", "plant", "water"]},

        {"id": 14,
         "name":"radiation",
         "type": "special",
         "weak": ["electricity", "fire", "undead"],
         "strong": ["alien", "chaos", "radiation", "plant"]},

        {"id": 15,
         "name":"undead",
         "type": "physical",
         "weak": ["air", "earth", "fire", "metal", "undead", "water"],
         "strong": ["alien", "chaos", "electricity", "holiness", "ice", "normal", "poison"]},

        {"id": 16,
         "name":"water",
         "type": "special",
         "weak": ["chaos", "electricity", "ice", "mututation", "plant", "poison", "water"],
         "strong": ["alien", "evil", "fire", "metal", "radiation"]}
    ]
}
